TaskoraApi/__init__.py
TaskoraApi/InstagramApi/__init__.py
TaskoraApi/InstagramApi/aiohttp_client.py
TaskoraApi/InstagramApi/httpx_client.py
TaskoraApi/InstagramApi/requests_client.py
TaskoraApi/QuizApi/__init__.py
TaskoraApi/QuizApi/aiohttp_client.py
TaskoraApi/QuizApi/httpx_client.py
TaskoraApi/QuizApi/requests_client.py
TaskoraApi/chatBot/__init__.py
TaskoraApi/chatBot/client.py
TaskoraApi/reCaptchaV3Solver/__init__.py
TaskoraApi/reCaptchaV3Solver/client.py
TaskoraApi-1.1.1.dist-info/METADATA
TaskoraApi-1.1.1.dist-info/WHEEL
TaskoraApi-1.1.1.dist-info/top_level.txt
TaskoraApi-1.1.1.dist-info/RECORD
