Metadata-Version: 2.1
Name: TaskoraApi
Version: 1.1.1
Summary: Python client for interacting with the QuizAPI, InstagramApi , chatBot and reChaptchaV3 Solver using aiohttp, httpx, or requests.
Home-page: https://github.com/yourusername/TaskoraApi
Author: Sam
Author-email: your_email@example.com
License: UNKNOWN
Platform: UNKNOWN
Classifier: Programming Language :: Python :: 3
Classifier: License :: OSI Approved :: MIT License
Classifier: Operating System :: OS Independent
Requires-Python: >=3.9
Requires-Dist: aiohttp >=3.8.0
Requires-Dist: httpx >=0.24.0
Requires-Dist: requests >=2.25.0
